{
 "name": "TAMBAT ISHWARI RUPESH RIDDHI from Smt. Vidyaben D. Gardi High School, Mulund",
 "standard": "1",
 "medium": "English",
 "schoolId": "671bcbb76991bc01e",
 "schoolName": "Smt. Vidyaben D. Gardi High School, Mulund",
 "examCentreId": "6559b76397c76ba07",
 "examCentreName": "Sharon English School, Mulund",
 "code": "1E1301010032",
 "status": "CHECKED",
 "score": "52",
 "rank": "",
 "rankSeq": "0",
 "remarks": "PASS",
 "remarks11": "PASS",
 "remarks12": "",
 "remarks21": "",
 "remarks22": "",
 "award": "",
 "mothersName": "RIDDHI",
 "firstName": "ISHWARI",
 "fathersName": "RUPESH",
 "surname": "TAMBAT",
 "score11": "52",
 "score12": "",
 "score21": "",
 "score22": ""
}