{
 "name": "KHAIRNAR YASH NITIN NISHA from Matoshree Gangubai Sambhaji Shinde, CBSE School, Mangaon",
 "standard": "1",
 "medium": "English",
 "schoolId": "671cd6e013457badc",
 "schoolName": "Matoshree Gangubai Sambhaji Shinde, CBSE School, Mangaon",
 "examCentreId": "65607256145fef686",
 "examCentreName": "S.N. Shipurkar English Medium School, Mangaon",
 "code": "1E1407010006",
 "status": "CHECKED",
 "score": "54",
 "rank": "",
 "rankSeq": "0",
 "remarks": "PASS",
 "remarks11": "PASS",
 "remarks12": "",
 "remarks21": "",
 "remarks22": "",
 "award": "",
 "mothersName": "NISHA",
 "firstName": "YASH",
 "fathersName": "NITIN",
 "surname": "KHAIRNAR",
 "score11": "54",
 "score12": "",
 "score21": "",
 "score22": ""
}