{
 "name": "MHAPARLE VIHAN VIKRANT UNNATI from New English School, Kalwa",
 "standard": "1",
 "medium": "English",
 "schoolId": "64fc4f1222d819cb1",
 "schoolName": "New English School, Kalwa",
 "examCentreId": "65599ecd59fdb29d2",
 "examCentreName": "S.V.P.M. English Primary School, Kalwa",
 "code": "1E1504010001",
 "status": "CHECKED",
 "score": "48",
 "rank": "",
 "rankSeq": "0",
 "remarks": "PASS",
 "remarks11": "PASS",
 "remarks12": "",
 "remarks21": "",
 "remarks22": "",
 "award": "",
 "mothersName": "UNNATI",
 "firstName": "VIHAN",
 "fathersName": "VIKRANT",
 "surname": "MHAPARLE",
 "score11": "48",
 "score12": "",
 "score21": "",
 "score22": ""
}