{
 "name": "BILE GARGI GANESH GITANJALI from N.G. Vartak English Medium School, Virar",
 "standard": "1",
 "medium": "English",
 "schoolId": "65225d3cecd34284c",
 "schoolName": "N.G. Vartak English Medium School, Virar",
 "examCentreId": "6559b5638215754ba",
 "examCentreName": "N.G. Vartak English Medium School, Virar",
 "code": "1E1605020009",
 "status": "CHECKED",
 "score": "10",
 "rank": "",
 "rankSeq": "0",
 "remarks": "FAIL",
 "remarks11": "FAIL",
 "remarks12": "",
 "remarks21": "",
 "remarks22": "",
 "award": "",
 "mothersName": "GITANJALI",
 "firstName": "GARGI",
 "fathersName": "GANESH",
 "surname": "BILE",
 "score11": "10",
 "score12": "",
 "score21": "",
 "score22": ""
}