{
 "name": "CHAUDHARI PRATYUSH NITIN NIKITA from N.G. Vartak English Medium School, Virar",
 "standard": "1",
 "medium": "English",
 "schoolId": "65225d3cecd34284c",
 "schoolName": "N.G. Vartak English Medium School, Virar",
 "examCentreId": "6559b5638215754ba",
 "examCentreName": "N.G. Vartak English Medium School, Virar",
 "code": "1E1605020010",
 "status": "CHECKED",
 "score": "36",
 "rank": "",
 "rankSeq": "0",
 "remarks": "PASS",
 "remarks11": "PASS",
 "remarks12": "",
 "remarks21": "",
 "remarks22": "",
 "award": "",
 "mothersName": "NIKITA",
 "firstName": "PRATYUSH",
 "fathersName": "NITIN",
 "surname": "CHAUDHARI",
 "score11": "36",
 "score12": "",
 "score21": "",
 "score22": ""
}