{
 "name": "WARIK SWARAJ AMIT ARPITA from S.P.S. Yojana Vidyalaya, Borivali",
 "standard": "1",
 "medium": "Marathi",
 "schoolId": "652a4137701b2c382",
 "schoolName": "S.P.S. Yojana Vidyalaya, Borivali",
 "examCentreId": "672228e60f8ba884a",
 "examCentreName": "Smt. Shushila Mahadev Padhye Prathmik Shala, Borivali",
 "code": "1M1204010049",
 "status": "CHECKED",
 "score": "58",
 "rank": "",
 "rankSeq": "0",
 "remarks": "PASS",
 "remarks11": "PASS",
 "remarks12": "",
 "remarks21": "",
 "remarks22": "",
 "award": "",
 "mothersName": "ARPITA",
 "firstName": "SWARAJ",
 "fathersName": "AMIT",
 "surname": "WARIK",
 "score11": "58",
 "score12": "",
 "score21": "",
 "score22": ""
}