{
 "name": "GHADE SANIDHYA SACHIN SIMARAN from Parag Vidyalaya, Bhandup",
 "standard": "1",
 "medium": "Marathi",
 "schoolId": "652918c952a60bc9e",
 "schoolName": "Parag Vidyalaya, Bhandup",
 "examCentreId": "65618a02b0963d721",
 "examCentreName": "Rajaram Sheth Vidyalaya, Bhandup",
 "code": "1M1302010056",
 "status": "CHECKED",
 "score": "18",
 "rank": "",
 "rankSeq": "0",
 "remarks": "FAIL",
 "remarks11": "FAIL",
 "remarks12": "",
 "remarks21": "",
 "remarks22": "",
 "award": "",
 "mothersName": "SIMARAN",
 "firstName": "SANIDHYA",
 "fathersName": "SACHIN",
 "surname": "GHADE",
 "score11": "18",
 "score12": "",
 "score21": "",
 "score22": ""
}