{
 "name": "BOKAMURKAR SAKSHAM SUNIL SUVARNA from S.V.P.M. Marathi Primary School, Kalwa",
 "standard": "1",
 "medium": "Semi",
 "schoolId": "6720eb42e3e891cf7",
 "schoolName": "S.V.P.M. Marathi Primary School, Kalwa",
 "examCentreId": "65599ecd59fdb29d2",
 "examCentreName": "S.V.P.M. English Primary School, Kalwa",
 "code": "1S1504010005",
 "status": "CHECKED",
 "score": "52",
 "rank": "",
 "rankSeq": "0",
 "remarks": "PASS",
 "remarks11": "PASS",
 "remarks12": "",
 "remarks21": "",
 "remarks22": "",
 "award": "",
 "mothersName": "SUVARNA",
 "firstName": "SAKSHAM",
 "fathersName": "SUNIL",
 "surname": "BOKAMURKAR",
 "score11": "52",
 "score12": "",
 "score21": "",
 "score22": ""
}