{
 "name": "KAMBLE REHANSHI ANANT RESHMA from Pandurang Vidyalay, Dombivali",
 "standard": "1",
 "medium": "Semi",
 "schoolId": "65278718807745ee2",
 "schoolName": "Pandurang Vidyalay, Dombivali",
 "examCentreId": "65599dc29469b833b",
 "examCentreName": "Pandurang Vidyalay, Dombivali",
 "code": "1S1503020026",
 "status": "CHECKED",
 "score": "36",
 "rank": "",
 "rankSeq": "0",
 "remarks": "PASS",
 "remarks11": "PASS",
 "remarks12": "",
 "remarks21": "",
 "remarks22": "",
 "award": "",
 "mothersName": "RESHMA",
 "firstName": "REHANSHI",
 "fathersName": "ANANT",
 "surname": "KAMBLE",
 "score11": "36",
 "score12": "",
 "score21": "",
 "score22": ""
}