{
 "name": "DABHOLKAR AAYUSH AMRUT AARYA from Abhinav little Angles Primary School, Borivali",
 "standard": "2",
 "medium": "English",
 "schoolId": "672229bdb7295213d",
 "schoolName": "Abhinav little Angles Primary School, Borivali",
 "examCentreId": "672228e60f8ba884a",
 "examCentreName": "Smt. Shushila Mahadev Padhye Prathmik Shala, Borivali",
 "code": "2E1204010011",
 "status": "CHECKED",
 "score": "60",
 "rank": "",
 "rankSeq": "0",
 "remarks": "PASS",
 "remarks11": "PASS",
 "remarks12": "",
 "remarks21": "",
 "remarks22": "",
 "award": "",
 "mothersName": "AARYA",
 "firstName": "AAYUSH",
 "fathersName": "AMRUT",
 "surname": "DABHOLKAR",
 "score11": "60",
 "score12": "",
 "score21": "",
 "score22": ""
}