{
 "name": "DHONDKAR PRAVYA JEEVAN GAURI from Loknete Ramsheth Thakur Eng. Med. School, kamothe",
 "standard": "2",
 "medium": "English",
 "schoolId": "6720e6a09abf0c643",
 "schoolName": "Loknete Ramsheth Thakur Eng. Med. School, kamothe",
 "examCentreId": "6720cd4c738391c25",
 "examCentreName": "M.A.D.P. Vidyalaya English Medium School, Kamothe",
 "code": "2E1412010018",
 "status": "CHECKED",
 "score": "70",
 "rank": "",
 "rankSeq": "0",
 "remarks": "PASS",
 "remarks11": "PASS",
 "remarks12": "",
 "remarks21": "",
 "remarks22": "",
 "award": "",
 "mothersName": "GAURI",
 "firstName": "PRAVYA",
 "fathersName": "JEEVAN",
 "surname": "DHONDKAR",
 "score11": "70",
 "score12": "",
 "score21": "",
 "score22": ""
}