{
 "name": "NAMASALE SWAYAM SANDEEP SAMRUDDHI from D.D. Alis Babasaheb Deshpande Primary School, Sion",
 "standard": "2",
 "medium": "Semi",
 "schoolId": "64fc47fc4aa71719c",
 "schoolName": "D.D. Alis Babasaheb Deshpande Primary School, Sion",
 "examCentreId": "6559abec537948fd0",
 "examCentreName": "D.D. Alis Babasaheb Deshpande Primary School, Sion",
 "code": "2S1306020084",
 "status": "CHECKED",
 "score": "56",
 "rank": "",
 "rankSeq": "0",
 "remarks": "PASS",
 "remarks11": "PASS",
 "remarks12": "",
 "remarks21": "",
 "remarks22": "",
 "award": "",
 "mothersName": "SAMRUDDHI",
 "firstName": "SWAYAM",
 "fathersName": "SANDEEP",
 "surname": "NAMASALE",
 "score11": "56",
 "score12": "",
 "score21": "",
 "score22": ""
}