{
 "name": "KHAN YUNUS YUSUF ANISA from Kai. Bhausaheb Bhor Vidyamandir, Ambernath",
 "standard": "2",
 "medium": "Semi",
 "schoolId": "6527902ec93c882d1",
 "schoolName": "Kai. Bhausaheb Bhor Vidyamandir, Ambernath",
 "examCentreId": "65599c604d93f2462",
 "examCentreName": "Balwadi Bhagini Mandal Primary School No. 1, Ambernath",
 "code": "2S1511010045",
 "status": "CHECKED",
 "score": "16",
 "rank": "",
 "rankSeq": "0",
 "remarks": "FAIL",
 "remarks11": "FAIL",
 "remarks12": "",
 "remarks21": "",
 "remarks22": "",
 "award": "",
 "mothersName": "ANISA",
 "firstName": "YUNUS",
 "fathersName": "YUSUF",
 "surname": "KHAN",
 "score11": "16",
 "score12": "",
 "score21": "",
 "score22": ""
}