{
 "name": "LENDE SANYUKTA SANTOSH RESHMA from Dr. Bedekar Vidyamandir, Thane",
 "standard": "2",
 "medium": "Semi",
 "schoolId": "6527a57b15e0d6eec",
 "schoolName": "Dr. Bedekar Vidyamandir, Thane",
 "examCentreId": "65599efe8edb57602",
 "examCentreName": "S.B. Firke English Vidyalay, Thane",
 "code": "2S1505010114",
 "status": "CHECKED",
 "score": "90",
 "rank": "",
 "rankSeq": "0",
 "remarks": "PASS",
 "remarks11": "PASS",
 "remarks12": "",
 "remarks21": "",
 "remarks22": "",
 "award": "",
 "mothersName": "RESHMA",
 "firstName": "SANYUKTA",
 "fathersName": "SANTOSH",
 "surname": "LENDE",
 "score11": "90",
 "score12": "",
 "score21": "",
 "score22": ""
}