{
 "name": "TAYDE ADITYA RAJU PALLAVI from Air India Modern School, Santacruz",
 "standard": "3",
 "medium": "English",
 "schoolId": "64fc4a29efae6e69b",
 "schoolName": "Air India Modern School, Santacruz",
 "examCentreId": "691831538282056c8",
 "examCentreName": "Air India Modern School, Santacruz",
 "code": "3E1205010032",
 "status": "CHECKED",
 "score": "142",
 "rank": "",
 "rankSeq": "0",
 "remarks": "PASS",
 "remarks11": "PASS",
 "remarks12": "PASS",
 "remarks21": "PASS",
 "remarks22": "PASS",
 "award": "",
 "mothersName": "PALLAVI",
 "firstName": "ADITYA",
 "fathersName": "RAJU",
 "surname": "TAYDE",
 "score11": "30",
 "score12": "46",
 "score21": "32",
 "score22": "34"
}