{
 "name": "MHATRE SHREEYASH SANJIT YOGITA from Chintamanrao Kelkar Vidyalay English Section, Alibaug",
 "standard": "3",
 "medium": "English",
 "schoolId": "652410e31fcff9f83",
 "schoolName": "Chintamanrao Kelkar Vidyalay English Section, Alibaug",
 "examCentreId": "6560715084b5409df",
 "examCentreName": "Chintamanrao Kelkar Vidyalay Marathi Section, Alibaug",
 "code": "3E1405010036",
 "status": "CHECKED",
 "score": "88",
 "rank": "",
 "rankSeq": "0",
 "remarks": "PASS",
 "remarks11": "PASS",
 "remarks12": "FAIL",
 "remarks21": "PASS",
 "remarks22": "PASS",
 "award": "",
 "mothersName": "YOGITA",
 "firstName": "SHREEYASH",
 "fathersName": "SANJIT",
 "surname": "MHATRE",
 "score11": "20",
 "score12": "22",
 "score21": "18",
 "score22": "28"
}