{
 "name": "SHINDE SWAYAM SWAPNIL SWARA from Matoshree Gangubai Sambhaji Shinde, CBSE School, Mangaon",
 "standard": "3",
 "medium": "English",
 "schoolId": "671cd6e013457badc",
 "schoolName": "Matoshree Gangubai Sambhaji Shinde, CBSE School, Mangaon",
 "examCentreId": "65607256145fef686",
 "examCentreName": "S.N. Shipurkar English Medium School, Mangaon",
 "code": "3E1407010020",
 "status": "CHECKED",
 "score": "158",
 "rank": "",
 "rankSeq": "0",
 "remarks": "PASS",
 "remarks11": "PASS",
 "remarks12": "PASS",
 "remarks21": "PASS",
 "remarks22": "PASS",
 "award": "",
 "mothersName": "SWARA",
 "firstName": "SWAYAM",
 "fathersName": "SWAPNIL",
 "surname": "SHINDE",
 "score11": "30",
 "score12": "64",
 "score21": "38",
 "score22": "26"
}