{
 "name": "KATALKAR PARI SANDESH PRACHI from G.E.S. New English School, Arathi",
 "standard": "3",
 "medium": "English",
 "schoolId": "671cf56a5080eef09",
 "schoolName": "G.E.S. New English School, Arathi",
 "examCentreId": "6560729eacbc3f19c",
 "examCentreName": "R.N. Raut Madhyamik Vidyalaya, Shriwardhan",
 "code": "3E1403010006",
 "status": "CHECKED",
 "score": "106",
 "rank": "",
 "rankSeq": "0",
 "remarks": "PASS",
 "remarks11": "FAIL",
 "remarks12": "PASS",
 "remarks21": "PASS",
 "remarks22": "PASS",
 "award": "",
 "mothersName": "PRACHI",
 "firstName": "PARI",
 "fathersName": "SANDESH",
 "surname": "KATALKAR",
 "score11": "10",
 "score12": "30",
 "score21": "24",
 "score22": "42"
}