{
 "name": "LOKAKSHI ABHANG KISHOR PRAGATI from Shri Mahavir Jain English School, Kalyan",
 "standard": "3",
 "medium": "English",
 "schoolId": "6527deecc24b4be44",
 "schoolName": "Shri Mahavir Jain English School, Kalyan",
 "examCentreId": "65599c96e24b69977",
 "examCentreName": "G.E.I's High School, Kalyan",
 "code": "3E1502010058",
 "status": "CHECKED",
 "score": "0",
 "rank": "",
 "rankSeq": "0",
 "remarks": "ABSENT",
 "remarks11": "ABSENT",
 "remarks12": "ABSENT",
 "remarks21": "ABSENT",
 "remarks22": "ABSENT",
 "award": "",
 "mothersName": "PRAGATI",
 "firstName": "ABHANG",
 "fathersName": "KISHOR",
 "surname": "LOKAKSHI",
 "score11": "0",
 "score12": "0",
 "score21": "0",
 "score22": "0"
}