{
 "name": "KUMTHEKAR IRA MIHIR SAYALI from S.P.M. English School Primary, Pune",
 "standard": "3",
 "medium": "English",
 "schoolId": "648ff1e0343e3e7b4",
 "schoolName": "S.P.M. English School Primary, Pune",
 "examCentreId": "671b8f816f97fbdd4",
 "examCentreName": "S.P.M. English School Primary, Pune",
 "code": "3E2101020036",
 "status": "CHECKED",
 "score": "0",
 "rank": "",
 "rankSeq": "0",
 "remarks": "ABSENT",
 "remarks11": "ABSENT",
 "remarks12": "ABSENT",
 "remarks21": "ABSENT",
 "remarks22": "ABSENT",
 "award": "",
 "mothersName": "SAYALI",
 "firstName": "IRA",
 "fathersName": "MIHIR",
 "surname": "KUMTHEKAR",
 "score11": "0",
 "score12": "0",
 "score21": "0",
 "score22": "0"
}