{
 "name": "WATAVE ISHITA MAYUR HARSHADA from St. Xavier's School, Nashik",
 "standard": "3",
 "medium": "English",
 "schoolId": "65251ecc8686d40f0",
 "schoolName": "St. Xavier's School, Nashik",
 "examCentreId": "6558d1899f82af555",
 "examCentreName": "Bluebell Primary School, Nashik",
 "code": "3E3101020071",
 "status": "CHECKED",
 "score": "128",
 "rank": "",
 "rankSeq": "0",
 "remarks": "PASS",
 "remarks11": "PASS",
 "remarks12": "PASS",
 "remarks21": "PASS",
 "remarks22": "PASS",
 "award": "",
 "mothersName": "HARSHADA",
 "firstName": "ISHITA",
 "fathersName": "MAYUR",
 "surname": "WATAVE",
 "score11": "22",
 "score12": "38",
 "score21": "28",
 "score22": "40"
}