{
 "name": "DALVI LAIBA MEHMOOD MIYA RUBEENA from Christ Jyoti Convent Primary School, Walope",
 "standard": "3",
 "medium": "English",
 "schoolId": "648ff1dfb3606e7fd",
 "schoolName": "Christ Jyoti Convent Primary School, Walope",
 "examCentreId": "6558d53ad220334d0",
 "examCentreName": "Mary Matha School, Kherdi",
 "code": "3E4402010048",
 "status": "CHECKED",
 "score": "126",
 "rank": "",
 "rankSeq": "0",
 "remarks": "PASS",
 "remarks11": "PASS",
 "remarks12": "PASS",
 "remarks21": "PASS",
 "remarks22": "PASS",
 "award": "",
 "mothersName": "RUBEENA",
 "firstName": "LAIBA",
 "fathersName": "MEHMOOD MIYA",
 "surname": "DALVI",
 "score11": "28",
 "score12": "36",
 "score21": "22",
 "score22": "40"
}