{
 "name": "GHAYAL SOHAM PRAKASH SAYALI from VPM. Vidya Mandir Marathi Primary Section, Dahisar",
 "standard": "3",
 "medium": "Marathi",
 "schoolId": "67222bec39a360435",
 "schoolName": "VPM. Vidya Mandir Marathi Primary Section, Dahisar",
 "examCentreId": "69188edc0ca137de4",
 "examCentreName": "Anudatt Vidyalaya Prathamik Vibhag, Kandivali",
 "code": "3M1203020056",
 "status": "CHECKED",
 "score": "108",
 "rank": "",
 "rankSeq": "0",
 "remarks": "PASS",
 "remarks11": "PASS",
 "remarks12": "FAIL",
 "remarks21": "PASS",
 "remarks22": "PASS",
 "award": "",
 "mothersName": "SAYALI",
 "firstName": "SOHAM",
 "fathersName": "PRAKASH",
 "surname": "GHAYAL",
 "score11": "20",
 "score12": "18",
 "score21": "36",
 "score22": "34"
}