{
 "name": "PATIL DAKSH RAKESH NEETA from N.P. School No. 1, Murud-Janjira",
 "standard": "3",
 "medium": "Marathi",
 "schoolId": "671cd753ae35df3dd",
 "schoolName": "N.P. School No. 1, Murud-Janjira",
 "examCentreId": "656071f794445b9e9",
 "examCentreName": "Nagarpalika School No. 1, Murud",
 "code": "3M1406010018",
 "status": "CHECKED",
 "score": "150",
 "rank": "",
 "rankSeq": "0",
 "remarks": "PASS",
 "remarks11": "PASS",
 "remarks12": "PASS",
 "remarks21": "PASS",
 "remarks22": "PASS",
 "award": "",
 "mothersName": "NEETA",
 "firstName": "DAKSH",
 "fathersName": "RAKESH",
 "surname": "PATIL",
 "score11": "38",
 "score12": "48",
 "score21": "32",
 "score22": "32"
}