{
 "name": "ZORE VEDIKA NAMDEV PUSHPA from K.E.S. Pirojbhai Bariya Primary School, Pezari",
 "standard": "3",
 "medium": "Marathi",
 "schoolId": "6524074ec07a07bef",
 "schoolName": "K.E.S. Pirojbhai Bariya Primary School, Pezari",
 "examCentreId": "6560710fbe84da0a3",
 "examCentreName": "K.E.S. Pirojbhai Bariya Prathamik Shala, Pezari",
 "code": "3M1411010079",
 "status": "RANKED",
 "score": "240",
 "rank": "99",
 "rankSeq": "99",
 "remarks": "PASS",
 "remarks11": "PASS",
 "remarks12": "PASS",
 "remarks21": "PASS",
 "remarks22": "PASS",
 "award": "Trophy (Small) + Medal + Certiﬁcate",
 "mothersName": "PUSHPA",
 "firstName": "VEDIKA",
 "fathersName": "NAMDEV",
 "surname": "ZORE",
 "score11": "42",
 "score12": "80",
 "score21": "42",
 "score22": "76"
}