{
 "name": "THETE YADNYA GURUNATH MONIKA from Vidya Vikas Primary School, Vangani",
 "standard": "3",
 "medium": "Marathi",
 "schoolId": "6914314eaa0288707",
 "schoolName": "Vidya Vikas Primary School, Vangani",
 "examCentreId": "69187dea6a9e8d988",
 "examCentreName": "Vidya Vikas Primary School, Vangani",
 "code": "3M1410010043",
 "status": "CHECKED",
 "score": "136",
 "rank": "",
 "rankSeq": "0",
 "remarks": "PASS",
 "remarks11": "PASS",
 "remarks12": "PASS",
 "remarks21": "PASS",
 "remarks22": "FAIL",
 "award": "",
 "mothersName": "MONIKA",
 "firstName": "YADNYA",
 "fathersName": "GURUNATH",
 "surname": "THETE",
 "score11": "42",
 "score12": "50",
 "score21": "22",
 "score22": "22"
}