{
 "name": "VARATHA VEDANT VIJAY VIDYA from Z.P. School, Potkhal",
 "standard": "3",
 "medium": "Marathi",
 "schoolId": "6522b28a9c6caeb08",
 "schoolName": "Z.P. School, Potkhal",
 "examCentreId": "6559b614e079bce5f",
 "examCentreName": "S.B.G.S Vidyalay, Alonde",
 "code": "3M1602010080",
 "status": "CHECKED",
 "score": "88",
 "rank": "",
 "rankSeq": "0",
 "remarks": "FAIL",
 "remarks11": "PASS",
 "remarks12": "FAIL",
 "remarks21": "PASS",
 "remarks22": "PASS",
 "award": "",
 "mothersName": "VIDYA",
 "firstName": "VEDANT",
 "fathersName": "VIJAY",
 "surname": "VARATHA",
 "score11": "14",
 "score12": "14",
 "score21": "28",
 "score22": "32"
}