{
 "name": "MUKANE RENIKA BHARAT BEBI from Z.P. School, Khoste",
 "standard": "3",
 "medium": "Marathi",
 "schoolId": "6522bbb34529ba89e",
 "schoolName": "Z.P. School, Khoste",
 "examCentreId": "6559b614e079bce5f",
 "examCentreName": "S.B.G.S Vidyalay, Alonde",
 "code": "3M1602010063",
 "status": "CHECKED",
 "score": "80",
 "rank": "",
 "rankSeq": "0",
 "remarks": "FAIL",
 "remarks11": "FAIL",
 "remarks12": "PASS",
 "remarks21": "PASS",
 "remarks22": "PASS",
 "award": "",
 "mothersName": "BEBI",
 "firstName": "RENIKA",
 "fathersName": "BHARAT",
 "surname": "MUKANE",
 "score11": "6",
 "score12": "28",
 "score21": "16",
 "score22": "30"
}