{
 "name": "JADHAV SANSKRITI YOGESH RADHIKA from Sadhana Prarthamik Vidyalay, Hadapsar",
 "standard": "3",
 "medium": "Marathi",
 "schoolId": "671b83d40f9a1bb43",
 "schoolName": "Sadhana Prarthamik Vidyalay, Hadapsar",
 "examCentreId": "671b8f9cd227896a1",
 "examCentreName": "Sadhana Prarthamik Vidyalay, Hadapsar",
 "code": "3M2103010057",
 "status": "CHECKED",
 "score": "156",
 "rank": "",
 "rankSeq": "0",
 "remarks": "PASS",
 "remarks11": "PASS",
 "remarks12": "PASS",
 "remarks21": "PASS",
 "remarks22": "PASS",
 "award": "",
 "mothersName": "RADHIKA",
 "firstName": "SANSKRITI",
 "fathersName": "YOGESH",
 "surname": "JADHAV",
 "score11": "36",
 "score12": "46",
 "score21": "26",
 "score22": "48"
}