{
 "name": "PATIL VAISHNAVI HANMANT MANISHA from Marathi Vidya Mandir, Porewadi",
 "standard": "3",
 "medium": "Marathi",
 "schoolId": "68c2c62b148828e8f",
 "schoolName": "Marathi Vidya Mandir, Porewadi",
 "examCentreId": "671b2fafaf35748f7",
 "examCentreName": "S.S. High School, Nesari",
 "code": "3M4105010047",
 "status": "CHECKED",
 "score": "216",
 "rank": "",
 "rankSeq": "0",
 "remarks": "PASS",
 "remarks11": "PASS",
 "remarks12": "PASS",
 "remarks21": "PASS",
 "remarks22": "PASS",
 "award": "",
 "mothersName": "MANISHA",
 "firstName": "VAISHNAVI",
 "fathersName": "HANMANT",
 "surname": "PATIL",
 "score11": "40",
 "score12": "68",
 "score21": "38",
 "score22": "70"
}