{
 "name": "SOLKAR RADHIKA VINOD SHRAVANI from Z.P. School, Valope No. 2",
 "standard": "3",
 "medium": "Marathi",
 "schoolId": "64dce37f2cb8b5635",
 "schoolName": "Z.P. School, Valope No. 2",
 "examCentreId": "6558d53ad220334d0",
 "examCentreName": "Mary Matha School, Kherdi",
 "code": "3M4402010333",
 "status": "CHECKED",
 "score": "198",
 "rank": "",
 "rankSeq": "0",
 "remarks": "PASS",
 "remarks11": "PASS",
 "remarks12": "PASS",
 "remarks21": "PASS",
 "remarks22": "PASS",
 "award": "",
 "mothersName": "SHRAVANI",
 "firstName": "RADHIKA",
 "fathersName": "VINOD",
 "surname": "SOLKAR",
 "score11": "44",
 "score12": "60",
 "score21": "34",
 "score22": "60"
}