{
 "name": "BECHAVADE SHLOK SAMIR SWARA from Z.P. School, Kamathe No. 2",
 "standard": "3",
 "medium": "Marathi",
 "schoolId": "648ff1dfbe086a029",
 "schoolName": "Z.P. School, Kamathe No. 2",
 "examCentreId": "6558d53ad220334d0",
 "examCentreName": "Mary Matha School, Kherdi",
 "code": "3M4402010239",
 "status": "CHECKED",
 "score": "68",
 "rank": "",
 "rankSeq": "0",
 "remarks": "FAIL",
 "remarks11": "FAIL",
 "remarks12": "FAIL",
 "remarks21": "PASS",
 "remarks22": "FAIL",
 "award": "",
 "mothersName": "SWARA",
 "firstName": "SHLOK",
 "fathersName": "SAMIR",
 "surname": "BECHAVADE",
 "score11": "10",
 "score12": "22",
 "score21": "14",
 "score22": "22"
}