{
 "name": "WANGANE MANAVI SUSHANT KAVERI from G.B. Jain Pri. Marathi School, Ladvali",
 "standard": "3",
 "medium": "Semi",
 "schoolId": "671cd6b883b817077",
 "schoolName": "G.B. Jain Pri. Marathi School, Ladvali",
 "examCentreId": "67208b51c12b99abb",
 "examCentreName": "Navyug English Medium School, Ladvali",
 "code": "3S1414010018",
 "status": "CHECKED",
 "score": "68",
 "rank": "",
 "rankSeq": "0",
 "remarks": "FAIL",
 "remarks11": "FAIL",
 "remarks12": "PASS",
 "remarks21": "FAIL",
 "remarks22": "FAIL",
 "award": "",
 "mothersName": "KAVERI",
 "firstName": "MANAVI",
 "fathersName": "SUSHANT",
 "surname": "WANGANE",
 "score11": "10",
 "score12": "32",
 "score21": "8",
 "score22": "18"
}