{
 "name": "BAPARDEKAR ARUSH ANKUSH AROHI from P.S. Jondhale Vidyamandir, Dombivali",
 "standard": "3",
 "medium": "Semi",
 "schoolId": "68f4ad5f3798283b8",
 "schoolName": "P.S. Jondhale Vidyamandir, Dombivali",
 "examCentreId": "6925b3e85daaf90f7",
 "examCentreName": "Shanti Nagar Vidyalay & Wisdom High School, Dombivali",
 "code": "3S1503030010",
 "status": "CHECKED",
 "score": "90",
 "rank": "",
 "rankSeq": "0",
 "remarks": "FAIL",
 "remarks11": "PASS",
 "remarks12": "FAIL",
 "remarks21": "PASS",
 "remarks22": "PASS",
 "award": "",
 "mothersName": "AROHI",
 "firstName": "ARUSH",
 "fathersName": "ANKUSH",
 "surname": "BAPARDEKAR",
 "score11": "18",
 "score12": "10",
 "score21": "32",
 "score22": "30"
}