{
 "name": "PADAVE MANASVI DEEPAK SHRAVANI from P.S. Jondhale Vidyamandir, Dombivali",
 "standard": "3",
 "medium": "Semi",
 "schoolId": "68f4ad5f3798283b8",
 "schoolName": "P.S. Jondhale Vidyamandir, Dombivali",
 "examCentreId": "6925b3e85daaf90f7",
 "examCentreName": "Shanti Nagar Vidyalay & Wisdom High School, Dombivali",
 "code": "3S1503030071",
 "status": "CHECKED",
 "score": "38",
 "rank": "",
 "rankSeq": "0",
 "remarks": "FAIL",
 "remarks11": "FAIL",
 "remarks12": "FAIL",
 "remarks21": "PASS",
 "remarks22": "FAIL",
 "award": "",
 "mothersName": "SHRAVANI",
 "firstName": "MANASVI",
 "fathersName": "DEEPAK",
 "surname": "PADAVE",
 "score11": "8",
 "score12": "8",
 "score21": "12",
 "score22": "10"
}