{
 "name": "DEORE ATHARV ATUL VIDYA from Shishu Vihar & Balak Mandir, Nashik",
 "standard": "3",
 "medium": "Semi",
 "schoolId": "65251df99ae7a0940",
 "schoolName": "Shishu Vihar & Balak Mandir, Nashik",
 "examCentreId": "6558d1ecbb8ae93fb",
 "examCentreName": "Swami Vivekanand Prathamik Vidyalaya, Morwadi",
 "code": "3S3101010133",
 "status": "CHECKED",
 "score": "126",
 "rank": "",
 "rankSeq": "0",
 "remarks": "PASS",
 "remarks11": "PASS",
 "remarks12": "FAIL",
 "remarks21": "PASS",
 "remarks22": "PASS",
 "award": "",
 "mothersName": "VIDYA",
 "firstName": "ATHARV",
 "fathersName": "ATUL",
 "surname": "DEORE",
 "score11": "24",
 "score12": "22",
 "score21": "42",
 "score22": "38"
}