{
 "name": "ATTARWALA AALIYA ABDULMANNAN KHADIJA from The Central School For The Deaf, Byculla",
 "standard": "4",
 "medium": "English",
 "schoolId": "64fc46334f26a3743",
 "schoolName": "The Central School For The Deaf, Byculla",
 "examCentreId": "69182be7c77e8c7c1",
 "examCentreName": "G.E.I. Chabildas Lallubhai Primary School, Dadar",
 "code": "4E1308010004",
 "status": "CHECKED",
 "score": "194",
 "rank": "",
 "rankSeq": "0",
 "remarks": "PASS",
 "remarks11": "PASS",
 "remarks12": "PASS",
 "remarks21": "PASS",
 "remarks22": "PASS",
 "award": "",
 "mothersName": "KHADIJA",
 "firstName": "AALIYA",
 "fathersName": "ABDULMANNAN",
 "surname": "ATTARWALA",
 "score11": "30",
 "score12": "68",
 "score21": "36",
 "score22": "60"
}