{
 "name": "LANDE VIRESH SOMNATH SUJATA from PNP Holy Child C.B.S.E. School, Veshvi",
 "standard": "4",
 "medium": "English",
 "schoolId": "671cfafa3a6adda91",
 "schoolName": "PNP Holy Child C.B.S.E. School, Veshvi",
 "examCentreId": "6560715084b5409df",
 "examCentreName": "Chintamanrao Kelkar Vidyalay Marathi Section, Alibaug",
 "code": "4E1405010023",
 "status": "CHECKED",
 "score": "146",
 "rank": "",
 "rankSeq": "0",
 "remarks": "PASS",
 "remarks11": "PASS",
 "remarks12": "PASS",
 "remarks21": "PASS",
 "remarks22": "PASS",
 "award": "",
 "mothersName": "SUJATA",
 "firstName": "VIRESH",
 "fathersName": "SOMNATH",
 "surname": "LANDE",
 "score11": "24",
 "score12": "46",
 "score21": "36",
 "score22": "40"
}