{
 "name": "SARUKTE KRUTIKA GOVIND KAVITA from New Ideal School & Jr. College, Vasind",
 "standard": "4",
 "medium": "English",
 "schoolId": "671bcd198434b9673",
 "schoolName": "New Ideal School & Jr. College, Vasind",
 "examCentreId": "6559b7ba03c5bab87",
 "examCentreName": "New Ideal School & Jr. College, Vasind",
 "code": "4E1512010057",
 "status": "CHECKED",
 "score": "114",
 "rank": "",
 "rankSeq": "0",
 "remarks": "PASS",
 "remarks11": "PASS",
 "remarks12": "PASS",
 "remarks21": "PASS",
 "remarks22": "FAIL",
 "award": "",
 "mothersName": "KAVITA",
 "firstName": "KRUTIKA",
 "fathersName": "GOVIND",
 "surname": "SARUKTE",
 "score11": "30",
 "score12": "28",
 "score21": "34",
 "score22": "22"
}