{
 "name": "JADHAV ARNAV RATNAKAR ASMI from Sau. A.K. Joshi English Medium School, Thane",
 "standard": "4",
 "medium": "English",
 "schoolId": "6720c06a1eba0d2fc",
 "schoolName": "Sau. A.K. Joshi English Medium School, Thane",
 "examCentreId": "65599efe8edb57602",
 "examCentreName": "S.B. Firke English Vidyalay, Thane",
 "code": "4E1505010018",
 "status": "CHECKED",
 "score": "172",
 "rank": "",
 "rankSeq": "0",
 "remarks": "PASS",
 "remarks11": "PASS",
 "remarks12": "PASS",
 "remarks21": "PASS",
 "remarks22": "PASS",
 "award": "",
 "mothersName": "ASMI",
 "firstName": "ARNAV",
 "fathersName": "RATNAKAR",
 "surname": "JADHAV",
 "score11": "32",
 "score12": "66",
 "score21": "42",
 "score22": "32"
}