{
 "name": "AJAGEKAR DIVYA SANDIP RAJASHREE from Utkarsha Vidyalaya English Medium Primary Section, Virar",
 "standard": "4",
 "medium": "English",
 "schoolId": "6522c91bdee72ceb1",
 "schoolName": "Utkarsha Vidyalaya English Medium Primary Section, Virar",
 "examCentreId": "6559b52d3543ad849",
 "examCentreName": "Utkarsha Vidyalaya, Virar",
 "code": "4E1605010003",
 "status": "CHECKED",
 "score": "90",
 "rank": "",
 "rankSeq": "0",
 "remarks": "PASS",
 "remarks11": "PASS",
 "remarks12": "PASS",
 "remarks21": "FAIL",
 "remarks22": "PASS",
 "award": "",
 "mothersName": "RAJASHREE",
 "firstName": "DIVYA",
 "fathersName": "SANDIP",
 "surname": "AJAGEKAR",
 "score11": "18",
 "score12": "28",
 "score21": "6",
 "score22": "38"
}