{
 "name": "HADAP TEJ SANDEEP SANCHITA from Shivaji Vidyalaya, Kajupada",
 "standard": "4",
 "medium": "Marathi",
 "schoolId": "64fc45228952237e7",
 "schoolName": "Shivaji Vidyalaya, Kajupada",
 "examCentreId": "6559ac44827120a60",
 "examCentreName": "Gandhi Bal Mandir, Kurla",
 "code": "4M1305010037",
 "status": "CHECKED",
 "score": "146",
 "rank": "",
 "rankSeq": "0",
 "remarks": "PASS",
 "remarks11": "PASS",
 "remarks12": "PASS",
 "remarks21": "PASS",
 "remarks22": "PASS",
 "award": "",
 "mothersName": "SANCHITA",
 "firstName": "TEJ",
 "fathersName": "SANDEEP",
 "surname": "HADAP",
 "score11": "32",
 "score12": "50",
 "score21": "34",
 "score22": "30"
}