{
 "name": "JANGAM PUNIT SACHIN PRIYANKA from Shivaji Shikshan Sanstha Prathamik Vidyalay, Ghatkopar",
 "standard": "4",
 "medium": "Marathi",
 "schoolId": "68bfdaac4623dd5e3",
 "schoolName": "Shivaji Shikshan Sanstha Prathamik Vidyalay, Ghatkopar",
 "examCentreId": "6559ad2c40ae4ffac",
 "examCentreName": "Shishu Vikas Prathamik Vidyalaya, Ghatkopar",
 "code": "4M1304010052",
 "status": "CHECKED",
 "score": "108",
 "rank": "",
 "rankSeq": "0",
 "remarks": "PASS",
 "remarks11": "PASS",
 "remarks12": "PASS",
 "remarks21": "PASS",
 "remarks22": "FAIL",
 "award": "",
 "mothersName": "PRIYANKA",
 "firstName": "PUNIT",
 "fathersName": "SACHIN",
 "surname": "JANGAM",
 "score11": "22",
 "score12": "38",
 "score21": "26",
 "score22": "22"
}