{
 "name": "PATIL BHARGAVI SANTOSH SANDHYA from R.Z.P. School, Chirvat",
 "standard": "4",
 "medium": "Marathi",
 "schoolId": "6720d11c65591b313",
 "schoolName": "R.Z.P. School, Chirvat",
 "examCentreId": "655a24b3b89fc0807",
 "examCentreName": "K.E.S.I.A.W. English Medium School, Panvel",
 "code": "4M1402010111",
 "status": "CHECKED",
 "score": "104",
 "rank": "",
 "rankSeq": "0",
 "remarks": "PASS",
 "remarks11": "PASS",
 "remarks12": "PASS",
 "remarks21": "PASS",
 "remarks22": "PASS",
 "award": "",
 "mothersName": "SANDHYA",
 "firstName": "BHARGAVI",
 "fathersName": "SANTOSH",
 "surname": "PATIL",
 "score11": "18",
 "score12": "32",
 "score21": "20",
 "score22": "34"
}