{
 "name": "THAKARE JIVIKA RUPESH RUNALI from Z.P. School, Wada",
 "standard": "4",
 "medium": "Marathi",
 "schoolId": "65225cc2259c78b4a",
 "schoolName": "Z.P. School, Wada",
 "examCentreId": "6559b5e18609f9b96",
 "examCentreName": "P.J. High School, Wada",
 "code": "4M1601010072",
 "status": "CHECKED",
 "score": "112",
 "rank": "",
 "rankSeq": "0",
 "remarks": "PASS",
 "remarks11": "PASS",
 "remarks12": "PASS",
 "remarks21": "PASS",
 "remarks22": "PASS",
 "award": "",
 "mothersName": "RUNALI",
 "firstName": "JIVIKA",
 "fathersName": "RUPESH",
 "surname": "THAKARE",
 "score11": "20",
 "score12": "46",
 "score21": "16",
 "score22": "30"
}