{
 "name": "HATTI ABHIRA SAMIR SNEHAL from Kilbil Vidya Mandir, Gadhinglaj",
 "standard": "4",
 "medium": "Marathi",
 "schoolId": "6515c0a50cb2c5062",
 "schoolName": "Kilbil Vidya Mandir, Gadhinglaj",
 "examCentreId": "671b320dce7f4d9ca",
 "examCentreName": "Shivraj College, Gadhinglaj",
 "code": "4M4101010045",
 "status": "CHECKED",
 "score": "172",
 "rank": "",
 "rankSeq": "0",
 "remarks": "PASS",
 "remarks11": "PASS",
 "remarks12": "PASS",
 "remarks21": "PASS",
 "remarks22": "PASS",
 "award": "",
 "mothersName": "SNEHAL",
 "firstName": "ABHIRA",
 "fathersName": "SAMIR",
 "surname": "HATTI",
 "score11": "32",
 "score12": "46",
 "score21": "42",
 "score22": "52"
}