{
 "name": "KADAM RUDRANI YUVRAJ SUCHITRA from Vidya Mandir, Sulgaon",
 "standard": "4",
 "medium": "Marathi",
 "schoolId": "671b2e101054b5c92",
 "schoolName": "Vidya Mandir, Sulgaon",
 "examCentreId": "6559950f2170aab5d",
 "examCentreName": "Vyankatrao Prathamik Vidya Mandir, Ajara",
 "code": "4M4102010029",
 "status": "CHECKED",
 "score": "222",
 "rank": "",
 "rankSeq": "0",
 "remarks": "PASS",
 "remarks11": "PASS",
 "remarks12": "PASS",
 "remarks21": "PASS",
 "remarks22": "PASS",
 "award": "",
 "mothersName": "SUCHITRA",
 "firstName": "RUDRANI",
 "fathersName": "YUVRAJ",
 "surname": "KADAM",
 "score11": "42",
 "score12": "72",
 "score21": "34",
 "score22": "74"
}