{
 "name": "DAHIPHALE YUVRAJ SUGRIV BHAGYSHREE from Mohite Patil Vidyalay, Mankhurd",
 "standard": "4",
 "medium": "Semi",
 "schoolId": "671bcac91846857e1",
 "schoolName": "Mohite Patil Vidyalay, Mankhurd",
 "examCentreId": "671bc574504da393b",
 "examCentreName": "Mohite Patil Vidyalay, Mankhurd",
 "code": "4S1309010047",
 "status": "CHECKED",
 "score": "220",
 "rank": "",
 "rankSeq": "0",
 "remarks": "PASS",
 "remarks11": "PASS",
 "remarks12": "PASS",
 "remarks21": "PASS",
 "remarks22": "PASS",
 "award": "",
 "mothersName": "BHAGYSHREE",
 "firstName": "YUVRAJ",
 "fathersName": "SUGRIV",
 "surname": "DAHIPHALE",
 "score11": "44",
 "score12": "80",
 "score21": "36",
 "score22": "60"
}