{
 "name": "MORE RUDRA RAVINDRA GEETA from Ma. Dadasaheb Dandekar Vidyalaya, Bhiwandi",
 "standard": "4",
 "medium": "Semi",
 "schoolId": "65278ca24d4ccd22e",
 "schoolName": "Ma. Dadasaheb Dandekar Vidyalaya, Bhiwandi",
 "examCentreId": "6549e9f06ca72e01e",
 "examCentreName": "GEI'S P.R. Vidyalay, Bhiwandi",
 "code": "4S1509010074",
 "status": "CHECKED",
 "score": "184",
 "rank": "",
 "rankSeq": "0",
 "remarks": "PASS",
 "remarks11": "PASS",
 "remarks12": "PASS",
 "remarks21": "PASS",
 "remarks22": "PASS",
 "award": "",
 "mothersName": "GEETA",
 "firstName": "RUDRA",
 "fathersName": "RAVINDRA",
 "surname": "MORE",
 "score11": "44",
 "score12": "56",
 "score21": "40",
 "score22": "44"
}