{
 "name": "WADAVALE SHREYA MANGESH VAIJAYANTI from Swami Vivekanand Vidyamandir Dattanagar, Dombivali",
 "standard": "4",
 "medium": "Semi",
 "schoolId": "652783ca41e4c1a74",
 "schoolName": "Swami Vivekanand Vidyamandir Dattanagar, Dombivali",
 "examCentreId": "6925b3e85daaf90f7",
 "examCentreName": "Shanti Nagar Vidyalay & Wisdom High School, Dombivali",
 "code": "4S1503030122",
 "status": "CHECKED",
 "score": "136",
 "rank": "",
 "rankSeq": "0",
 "remarks": "PASS",
 "remarks11": "PASS",
 "remarks12": "PASS",
 "remarks21": "PASS",
 "remarks22": "PASS",
 "award": "",
 "mothersName": "VAIJAYANTI",
 "firstName": "SHREYA",
 "fathersName": "MANGESH",
 "surname": "WADAVALE",
 "score11": "28",
 "score12": "40",
 "score21": "28",
 "score22": "40"
}