{
 "name": "THAKARE CHARAN KAPIL KAVYA from Utkarsha Vidyamandir, Wada",
 "standard": "4",
 "medium": "Semi",
 "schoolId": "6522d21e805d94553",
 "schoolName": "Utkarsha Vidyamandir, Wada",
 "examCentreId": "6559b5e18609f9b96",
 "examCentreName": "P.J. High School, Wada",
 "code": "4S1601010132",
 "status": "CHECKED",
 "score": "132",
 "rank": "",
 "rankSeq": "0",
 "remarks": "PASS",
 "remarks11": "PASS",
 "remarks12": "PASS",
 "remarks21": "PASS",
 "remarks22": "PASS",
 "award": "",
 "mothersName": "KAVYA",
 "firstName": "CHARAN",
 "fathersName": "KAPIL",
 "surname": "THAKARE",
 "score11": "22",
 "score12": "50",
 "score21": "28",
 "score22": "32"
}