{
 "name": "PACHADKAR AAYUSH SANJAY SAMRUDDHI from Gurukul Vidya Mandir, Gunade",
 "standard": "4",
 "medium": "Semi",
 "schoolId": "648ff1dfb9f2d7d7d",
 "schoolName": "Gurukul Vidya Mandir, Gunade",
 "examCentreId": "6558d53ad220334d0",
 "examCentreName": "Mary Matha School, Kherdi",
 "code": "4S4402010351",
 "status": "CHECKED",
 "score": "214",
 "rank": "",
 "rankSeq": "0",
 "remarks": "PASS",
 "remarks11": "PASS",
 "remarks12": "PASS",
 "remarks21": "PASS",
 "remarks22": "PASS",
 "award": "",
 "mothersName": "SAMRUDDHI",
 "firstName": "AAYUSH",
 "fathersName": "SANJAY",
 "surname": "PACHADKAR",
 "score11": "36",
 "score12": "76",
 "score21": "38",
 "score22": "64"
}