{
 "name": "ZOMBADE JAY SATISH POONAM from S.C.D. Barfiwala High School, Andheri",
 "standard": "6",
 "medium": "English",
 "schoolId": "652926a6e29a80fea",
 "schoolName": "S.C.D. Barfiwala High School, Andheri",
 "examCentreId": "65618a57bf20a5223",
 "examCentreName": "J.E.S. English School, Jogeshwari",
 "code": "6E1202010082",
 "status": "CHECKED",
 "score": "120",
 "rank": "",
 "rankSeq": "0",
 "remarks": "PASS",
 "remarks11": "PASS",
 "remarks12": "PASS",
 "remarks21": "PASS",
 "remarks22": "PASS",
 "award": "",
 "mothersName": "POONAM",
 "firstName": "JAY",
 "fathersName": "SATISH",
 "surname": "ZOMBADE",
 "score11": "28",
 "score12": "34",
 "score21": "18",
 "score22": "40"
}