{
 "name": "CHANDAN RAYANSH RAVINDRA RADHIKA from K.E.S. English Medium School, Karjat",
 "standard": "6",
 "medium": "English",
 "schoolId": "6529067eb5820b727",
 "schoolName": "K.E.S. English Medium School, Karjat",
 "examCentreId": "655a23c1cf2ff1572",
 "examCentreName": "Sharda Mandir English Medium School, Karjat",
 "code": "6E1401010003",
 "status": "CHECKED",
 "score": "120",
 "rank": "",
 "rankSeq": "0",
 "remarks": "PASS",
 "remarks11": "PASS",
 "remarks12": "PASS",
 "remarks21": "PASS",
 "remarks22": "PASS",
 "award": "",
 "mothersName": "RADHIKA",
 "firstName": "RAYANSH",
 "fathersName": "RAVINDRA",
 "surname": "CHANDAN",
 "score11": "26",
 "score12": "36",
 "score21": "24",
 "score22": "34"
}