{
 "name": "SHINDE AARADHYA VIKRAM POOJA from Gurukul International School, ICSE Badlapur",
 "standard": "6",
 "medium": "English",
 "schoolId": "67207d70e52bf612d",
 "schoolName": "Gurukul International School, ICSE Badlapur",
 "examCentreId": "655a233a8bc071a2e",
 "examCentreName": "Gurukul English Medium School, Badlapur",
 "code": "6E1501010051",
 "status": "CHECKED",
 "score": "164",
 "rank": "",
 "rankSeq": "0",
 "remarks": "PASS",
 "remarks11": "PASS",
 "remarks12": "PASS",
 "remarks21": "PASS",
 "remarks22": "PASS",
 "award": "",
 "mothersName": "POOJA",
 "firstName": "AARADHYA",
 "fathersName": "VIKRAM",
 "surname": "SHINDE",
 "score11": "28",
 "score12": "48",
 "score21": "28",
 "score22": "60"
}