{
 "name": "GODE JEET SUBHASH MONIKA from D.B. Jadhav English School, Bhiwandi",
 "standard": "6",
 "medium": "English",
 "schoolId": "65278f89517b264b5",
 "schoolName": "D.B. Jadhav English School, Bhiwandi",
 "examCentreId": "65599c96e24b69977",
 "examCentreName": "G.E.I's High School, Kalyan",
 "code": "6E1502010030",
 "status": "CHECKED",
 "score": "94",
 "rank": "",
 "rankSeq": "0",
 "remarks": "PASS",
 "remarks11": "PASS",
 "remarks12": "PASS",
 "remarks21": "PASS",
 "remarks22": "PASS",
 "award": "",
 "mothersName": "MONIKA",
 "firstName": "JEET",
 "fathersName": "SUBHASH",
 "surname": "GODE",
 "score11": "20",
 "score12": "34",
 "score21": "16",
 "score22": "24"
}