{
 "name": "GIRI RADHA GAYADEENPRASAD GUDIYA from National English School, Kudus",
 "standard": "6",
 "medium": "English",
 "schoolId": "6522cb1898375d0c3",
 "schoolName": "National English School, Kudus",
 "examCentreId": "6559b66f6cc13b4fb",
 "examCentreName": "National English School, Kudus",
 "code": "6E1604010008",
 "status": "CHECKED",
 "score": "74",
 "rank": "",
 "rankSeq": "0",
 "remarks": "FAIL",
 "remarks11": "PASS",
 "remarks12": "PASS",
 "remarks21": "PASS",
 "remarks22": "FAIL",
 "award": "",
 "mothersName": "GUDIYA",
 "firstName": "RADHA",
 "fathersName": "GAYADEENPRASAD",
 "surname": "GIRI",
 "score11": "16",
 "score12": "26",
 "score21": "12",
 "score22": "20"
}