{
 "name": "PATOLE MANAN SATISH SANCHITA from Saraswati Vidyalay & Jr. College, Vasind",
 "standard": "6",
 "medium": "Marathi",
 "schoolId": "671bcd6e7270f8a8f",
 "schoolName": "Saraswati Vidyalay & Jr. College, Vasind",
 "examCentreId": "69187c28095dcc8a1",
 "examCentreName": "Sharda English Medium School, Vasind",
 "code": "6M1512020011",
 "status": "CHECKED",
 "score": "152",
 "rank": "",
 "rankSeq": "0",
 "remarks": "PASS",
 "remarks11": "PASS",
 "remarks12": "PASS",
 "remarks21": "PASS",
 "remarks22": "PASS",
 "award": "",
 "mothersName": "SANCHITA",
 "firstName": "MANAN",
 "fathersName": "SATISH",
 "surname": "PATOLE",
 "score11": "26",
 "score12": "44",
 "score21": "18",
 "score22": "64"
}