{
 "name": "NAIK SHRUTI SANDEEP SAYALI from Laxmi Vidyamandir, Kalwa",
 "standard": "6",
 "medium": "Marathi",
 "schoolId": "6527a21965fbf145d",
 "schoolName": "Laxmi Vidyamandir, Kalwa",
 "examCentreId": "65599ecd59fdb29d2",
 "examCentreName": "S.V.P.M. English Primary School, Kalwa",
 "code": "6M1504010007",
 "status": "CHECKED",
 "score": "80",
 "rank": "",
 "rankSeq": "0",
 "remarks": "FAIL",
 "remarks11": "PASS",
 "remarks12": "FAIL",
 "remarks21": "FAIL",
 "remarks22": "PASS",
 "award": "",
 "mothersName": "SAYALI",
 "firstName": "SHRUTI",
 "fathersName": "SANDEEP",
 "surname": "NAIK",
 "score11": "18",
 "score12": "16",
 "score21": "10",
 "score22": "36"
}