{
 "name": "WARDE PRATIKSHA SHIVA RANI from M.R. Sarda Kanya Vidya Mandir, Nashik",
 "standard": "6",
 "medium": "Marathi",
 "schoolId": "671ba8e813a9414fa",
 "schoolName": "M.R. Sarda Kanya Vidya Mandir, Nashik",
 "examCentreId": "6558d1ecbb8ae93fb",
 "examCentreName": "Swami Vivekanand Prathamik Vidyalaya, Morwadi",
 "code": "6M3101010032",
 "status": "CHECKED",
 "score": "78",
 "rank": "",
 "rankSeq": "0",
 "remarks": "FAIL",
 "remarks11": "FAIL",
 "remarks12": "PASS",
 "remarks21": "PASS",
 "remarks22": "PASS",
 "award": "",
 "mothersName": "RANI",
 "firstName": "PRATIKSHA",
 "fathersName": "SHIVA",
 "surname": "WARDE",
 "score11": "6",
 "score12": "26",
 "score21": "20",
 "score22": "26"
}