{
 "name": "ARDALKAR SIDDHI SUDHAKAR SHITAL from New English School, Kaulage",
 "standard": "6",
 "medium": "Marathi",
 "schoolId": "671b39646e992e178",
 "schoolName": "New English School, Kaulage",
 "examCentreId": "671b320dce7f4d9ca",
 "examCentreName": "Shivraj College, Gadhinglaj",
 "code": "6M4101010008",
 "status": "RANKED",
 "score": "246",
 "rank": "63",
 "rankSeq": "63",
 "remarks": "PASS",
 "remarks11": "PASS",
 "remarks12": "PASS",
 "remarks21": "PASS",
 "remarks22": "PASS",
 "award": "Trophy (Small) + Medal + Certiﬁcate",
 "mothersName": "SHITAL",
 "firstName": "SIDDHI",
 "fathersName": "SUDHAKAR",
 "surname": "ARDALKAR",
 "score11": "46",
 "score12": "82",
 "score21": "28",
 "score22": "90"
}