{
 "name": "KOKATE SARVESH VIKAS SWATI from Yogi Shri Arvind Gurukul, Badlapur",
 "standard": "6",
 "medium": "Semi",
 "schoolId": "652a92c1151b957f8",
 "schoolName": "Yogi Shri Arvind Gurukul, Badlapur",
 "examCentreId": "655a236c07ef25bbc",
 "examCentreName": "Panna English High School, Badlapur",
 "code": "6S1501020046",
 "status": "CHECKED",
 "score": "82",
 "rank": "",
 "rankSeq": "0",
 "remarks": "PASS",
 "remarks11": "PASS",
 "remarks12": "PASS",
 "remarks21": "PASS",
 "remarks22": "PASS",
 "award": "",
 "mothersName": "SWATI",
 "firstName": "SARVESH",
 "fathersName": "VIKAS",
 "surname": "KOKATE",
 "score11": "16",
 "score12": "24",
 "score21": "14",
 "score22": "28"
}