{
 "name": "SHIRSAT AARUSHI CHANDRAKANT YOGITA from Takshashila Vidyalay, Ulhasnagar",
 "standard": "6",
 "medium": "Semi",
 "schoolId": "671bcca31b85c2ef1",
 "schoolName": "Takshashila Vidyalay, Ulhasnagar",
 "examCentreId": "6559b85e2944be58a",
 "examCentreName": "Century Rayon Primary School, Shahad",
 "code": "6S1515010021",
 "status": "CHECKED",
 "score": "104",
 "rank": "",
 "rankSeq": "0",
 "remarks": "PASS",
 "remarks11": "PASS",
 "remarks12": "PASS",
 "remarks21": "FAIL",
 "remarks22": "PASS",
 "award": "",
 "mothersName": "YOGITA",
 "firstName": "AARUSHI",
 "fathersName": "CHANDRAKANT",
 "surname": "SHIRSAT",
 "score11": "26",
 "score12": "30",
 "score21": "10",
 "score22": "38"
}