{
 "name": "JAGADE PARTH KAUSTUBH KADAMBARI from C.R.M. Oak High School, Kalyan",
 "standard": "6",
 "medium": "Semi",
 "schoolId": "6527fac4b910aa245",
 "schoolName": "C.R.M. Oak High School, Kalyan",
 "examCentreId": "65599cdde87d91769",
 "examCentreName": "Achiever's Public High School, Kalyan",
 "code": "6S1502020017",
 "status": "CHECKED",
 "score": "202",
 "rank": "",
 "rankSeq": "0",
 "remarks": "PASS",
 "remarks11": "PASS",
 "remarks12": "PASS",
 "remarks21": "PASS",
 "remarks22": "PASS",
 "award": "",
 "mothersName": "KADAMBARI",
 "firstName": "PARTH",
 "fathersName": "KAUSTUBH",
 "surname": "JAGADE",
 "score11": "32",
 "score12": "68",
 "score21": "32",
 "score22": "70"
}