{
 "name": "GHAG AARADHYA SANDEEP PRAGATI from Jindal Vidya Mandir, Salav",
 "standard": "7",
 "medium": "English",
 "schoolId": "6523d1599bc913815",
 "schoolName": "Jindal Vidya Mandir, Salav",
 "examCentreId": "672089d3e91832a78",
 "examCentreName": "Jindal Vidya Mandir, Salav",
 "code": "7E1416010003",
 "status": "CHECKED",
 "score": "2",
 "rank": "",
 "rankSeq": "0",
 "remarks": "ABSENT",
 "remarks11": "ABSENT",
 "remarks12": "ABSENT",
 "remarks21": "ABSENT",
 "remarks22": "ABSENT",
 "award": "",
 "mothersName": "PRAGATI",
 "firstName": "AARADHYA",
 "fathersName": "SANDEEP",
 "surname": "GHAG",
 "score11": "0",
 "score12": "0",
 "score21": "0",
 "score22": "2"
}