{
 "name": "PRAJAPATI DIVYA VINOD RINKU from Sharda English School, Diksal",
 "standard": "7",
 "medium": "English",
 "schoolId": "65290a3d5560ec889",
 "schoolName": "Sharda English School, Diksal",
 "examCentreId": "655a2470a85a5e2c7",
 "examCentreName": "Sharda English School, Diksal",
 "code": "7E1409010015",
 "status": "CHECKED",
 "score": "128",
 "rank": "",
 "rankSeq": "0",
 "remarks": "PASS",
 "remarks11": "PASS",
 "remarks12": "PASS",
 "remarks21": "PASS",
 "remarks22": "PASS",
 "award": "",
 "mothersName": "RINKU",
 "firstName": "DIVYA",
 "fathersName": "VINOD",
 "surname": "PRAJAPATI",
 "score11": "28",
 "score12": "28",
 "score21": "28",
 "score22": "44"
}