{
 "name": "KAGNE AROHI RAVINDRA ANUJA from Don Bosco High School, Kalyan",
 "standard": "7",
 "medium": "English",
 "schoolId": "6527df5e3325261ad",
 "schoolName": "Don Bosco High School, Kalyan",
 "examCentreId": "65599c96e24b69977",
 "examCentreName": "G.E.I's High School, Kalyan",
 "code": "7E1502010028",
 "status": "CHECKED",
 "score": "188",
 "rank": "",
 "rankSeq": "0",
 "remarks": "PASS",
 "remarks11": "PASS",
 "remarks12": "PASS",
 "remarks21": "PASS",
 "remarks22": "PASS",
 "award": "",
 "mothersName": "ANUJA",
 "firstName": "AROHI",
 "fathersName": "RAVINDRA",
 "surname": "KAGNE",
 "score11": "44",
 "score12": "38",
 "score21": "42",
 "score22": "64"
}