{
 "name": "PINJARI AALIYAH SALIM AAYESHA from GEI's English Medium School, Kalyan",
 "standard": "7",
 "medium": "English",
 "schoolId": "6527d6a8e99cf6da4",
 "schoolName": "GEI's English Medium School, Kalyan",
 "examCentreId": "65599c96e24b69977",
 "examCentreName": "G.E.I's High School, Kalyan",
 "code": "7E1502010060",
 "status": "RANKED",
 "score": "224",
 "rank": "135",
 "rankSeq": "135",
 "remarks": "PASS",
 "remarks11": "PASS",
 "remarks12": "PASS",
 "remarks21": "PASS",
 "remarks22": "PASS",
 "award": "Medal + Certiﬁcate",
 "mothersName": "AAYESHA",
 "firstName": "AALIYAH",
 "fathersName": "SALIM",
 "surname": "PINJARI",
 "score11": "42",
 "score12": "62",
 "score21": "46",
 "score22": "74"
}