{
 "name": "AGIWALE PRACHLIT RITESH PUNAM from Sri Vani Vidyashala High School, Kalyan",
 "standard": "7",
 "medium": "English",
 "schoolId": "6527f8add34184e2d",
 "schoolName": "Sri Vani Vidyashala High School, Kalyan",
 "examCentreId": "65599c96e24b69977",
 "examCentreName": "G.E.I's High School, Kalyan",
 "code": "7E1502010002",
 "status": "CHECKED",
 "score": "182",
 "rank": "",
 "rankSeq": "0",
 "remarks": "PASS",
 "remarks11": "PASS",
 "remarks12": "PASS",
 "remarks21": "PASS",
 "remarks22": "PASS",
 "award": "",
 "mothersName": "PUNAM",
 "firstName": "PRACHLIT",
 "fathersName": "RITESH",
 "surname": "AGIWALE",
 "score11": "32",
 "score12": "48",
 "score21": "34",
 "score22": "68"
}