{
 "name": "GANDHI HRISHANK PARAS MADHUBALA from S.P.M. English School Secondary, Pune",
 "standard": "7",
 "medium": "English",
 "schoolId": "64f96876e440b0f9f",
 "schoolName": "S.P.M. English School Secondary, Pune",
 "examCentreId": "671b8f816f97fbdd4",
 "examCentreName": "S.P.M. English School Primary, Pune",
 "code": "7E2101020004",
 "status": "RANKED",
 "score": "268",
 "rank": "10",
 "rankSeq": "10",
 "remarks": "PASS",
 "remarks11": "PASS",
 "remarks12": "PASS",
 "remarks21": "PASS",
 "remarks22": "PASS",
 "award": "Cash Prize (1000) + Trophy (Medium) + Certiﬁcate",
 "mothersName": "MADHUBALA",
 "firstName": "HRISHANK",
 "fathersName": "PARAS",
 "surname": "GANDHI",
 "score11": "50",
 "score12": "92",
 "score21": "42",
 "score22": "84"
}