{
 "name": "PRABHUDEASAI SAMARTH VAIBHAV ARPITA from SPM English Medium School, Parshuram",
 "standard": "7",
 "medium": "English",
 "schoolId": "648ff1dfbbc7c792a",
 "schoolName": "SPM English Medium School, Parshuram",
 "examCentreId": "6558d53ad220334d0",
 "examCentreName": "Mary Matha School, Kherdi",
 "code": "7E4402010118",
 "status": "CHECKED",
 "score": "142",
 "rank": "",
 "rankSeq": "0",
 "remarks": "PASS",
 "remarks11": "PASS",
 "remarks12": "PASS",
 "remarks21": "PASS",
 "remarks22": "PASS",
 "award": "",
 "mothersName": "ARPITA",
 "firstName": "SAMARTH",
 "fathersName": "VAIBHAV",
 "surname": "PRABHUDEASAI",
 "score11": "28",
 "score12": "36",
 "score21": "36",
 "score22": "42"
}