{
 "name": "MANGALE VEDANT JAYWANT CHITRA from New English School, Kaulage",
 "standard": "7",
 "medium": "Marathi",
 "schoolId": "671b39646e992e178",
 "schoolName": "New English School, Kaulage",
 "examCentreId": "671b320dce7f4d9ca",
 "examCentreName": "Shivraj College, Gadhinglaj",
 "code": "7M4101010130",
 "status": "CHECKED",
 "score": "200",
 "rank": "",
 "rankSeq": "0",
 "remarks": "PASS",
 "remarks11": "PASS",
 "remarks12": "PASS",
 "remarks21": "PASS",
 "remarks22": "PASS",
 "award": "",
 "mothersName": "CHITRA",
 "firstName": "VEDANT",
 "fathersName": "JAYWANT",
 "surname": "MANGALE",
 "score11": "38",
 "score12": "60",
 "score21": "28",
 "score22": "74"
}