{
 "name": "PATIL SANSKAR SACHIN MAHADEVI from Vidya Mandir, Shippur",
 "standard": "7",
 "medium": "Marathi",
 "schoolId": "651657094e2fd8f9b",
 "schoolName": "Vidya Mandir, Shippur",
 "examCentreId": "671b320dce7f4d9ca",
 "examCentreName": "Shivraj College, Gadhinglaj",
 "code": "7M4101010170",
 "status": "CHECKED",
 "score": "4",
 "rank": "",
 "rankSeq": "0",
 "remarks": "ABSENT",
 "remarks11": "ABSENT",
 "remarks12": "ABSENT",
 "remarks21": "ABSENT",
 "remarks22": "ABSENT",
 "award": "",
 "mothersName": "MAHADEVI",
 "firstName": "SANSKAR",
 "fathersName": "SACHIN",
 "surname": "PATIL",
 "score11": "2",
 "score12": "0",
 "score21": "0",
 "score22": "2"
}