{
 "name": "SABLE HEMRAJ BALIRAM NAMRATA from Asmita Sanchalit J.A. Madhyamik Vidyalaya, Jogeshwari",
 "standard": "7",
 "medium": "Semi",
 "schoolId": "652a247b94c34c096",
 "schoolName": "Asmita Sanchalit J.A. Madhyamik Vidyalaya, Jogeshwari",
 "examCentreId": "65618a57bf20a5223",
 "examCentreName": "J.E.S. English School, Jogeshwari",
 "code": "7S1202010061",
 "status": "CHECKED",
 "score": "174",
 "rank": "",
 "rankSeq": "0",
 "remarks": "PASS",
 "remarks11": "PASS",
 "remarks12": "PASS",
 "remarks21": "PASS",
 "remarks22": "PASS",
 "award": "",
 "mothersName": "NAMRATA",
 "firstName": "HEMRAJ",
 "fathersName": "BALIRAM",
 "surname": "SABLE",
 "score11": "30",
 "score12": "48",
 "score21": "42",
 "score22": "54"
}